score.ctx-0.6.2-py3.7-nspkg.pth
score/ctx/__init__.py
score/ctx/_init.py
score/ctx/cli.py
score.ctx-0.6.2.dist-info/COPYING.LESSER.txt
score.ctx-0.6.2.dist-info/METADATA
score.ctx-0.6.2.dist-info/WHEEL
score.ctx-0.6.2.dist-info/namespace_packages.txt
score.ctx-0.6.2.dist-info/top_level.txt
score.ctx-0.6.2.dist-info/RECORD
